Metadata-Version: 2.4
Name: iflow-mcp_egyptianego17-documentation
Version: 0.1.0
Summary: Add your description here
License-File: LICENSE
Requires-Python: >=3.11
Requires-Dist: aiosmtplib>=3.0.0
Requires-Dist: email-validator>=2.0.0
Requires-Dist: mcp[cli]>=1.3.0
Requires-Dist: pydantic>=2.0.0
Requires-Dist: python-dotenv>=1.0.0
